obsws_python/__init__.py
obsws_python/baseclient.py
obsws_python/callback.py
obsws_python/error.py
obsws_python/events.py
obsws_python/reqs.py
obsws_python/subs.py
obsws_python/util.py
obsws_python/version.py
obsws_python-1.7.2.dist-info/METADATA
obsws_python-1.7.2.dist-info/WHEEL
obsws_python-1.7.2.dist-info/licenses/LICENSE
obsws_python-1.7.2.dist-info/RECORD
