Metadata-Version: 2.4
Name: obsws-python
Version: 1.7.2
Summary: A Python SDK for OBS Studio WebSocket v5.0
Project-URL: Homepage, https://github.com/aatikturk/obsws-python
Author-email: Adem Atikturk <aatikturk@gmail.com>
License: GPL-3.0-only
License-File: LICENSE
Requires-Python: >=3.9
Requires-Dist: tomli>=2.0.1; python_version < '3.11'
Requires-Dist: websocket-client
